{
  "id": 5237,
  "chapter_id": 66,
  "verse_key": "66:8",
  "hizb_number": 56,
  "rub_el_hizb_number": 224,
  "ruku_number": 497,
  "manzil_number": 7,
  "page_number": 561,
  "juz_number": 28,
  "text_uthmani": "يَـٰٓأَيُّهَا ٱلَّذِينَ ءَامَنُوا۟ تُوبُوٓا۟ إِلَى ٱللَّهِ تَوْبَةً نَّصُوحًا عَسَىٰ رَبُّكُمْ أَن يُكَفِّرَ عَنكُمْ سَيِّـَٔاتِكُمْ وَيُدْخِلَكُمْ جَنَّـٰتٍ تَجْرِى مِن تَحْتِهَا ٱلْأَنْهَـٰرُ يَوْمَ لَا يُخْزِى ٱللَّهُ ٱلنَّبِىَّ وَٱلَّذِينَ ءَامَنُوا۟ مَعَهُۥ ۖ نُورُهُمْ يَسْعَىٰ بَيْنَ أَيْدِيهِمْ وَبِأَيْمَـٰنِهِمْ يَقُولُونَ رَبَّنَآ أَتْمِمْ لَنَا نُورَنَا وَٱغْفِرْ لَنَآ ۖ إِنَّكَ عَلَىٰ كُلِّ شَىْءٍ قَدِيرٌ",
  "audio_url": "https://download.quranicaudio.com/qdc/mishari_al_afasy/murattal/66.mp3",
  "words": [
    {
      "id": 8990,
      "line_number": 1,
      "audio_url": "https://audio.qurancdn.com/wbw/066_008_001.mp3",
      "text": "يَـٰٓأَيُّهَا",
      "translation": "wahai",
      "transliteration": "yāayyuhā"
    },
    {
      "id": 8991,
      "line_number": 1,
      "audio_url": "https://audio.qurancdn.com/wbw/066_008_002.mp3",
      "text": "ٱلَّذِينَ",
      "translation": "orang-orang yang",
      "transliteration": "alladhīna"
    },
    {
      "id": 8992,
      "line_number": 1,
      "audio_url": "https://audio.qurancdn.com/wbw/066_008_003.mp3",
      "text": "ءَامَنُوا۟",
      "translation": "beriman",
      "transliteration": "āmanū"
    },
    {
      "id": 8993,
      "line_number": 1,
      "audio_url": "https://audio.qurancdn.com/wbw/066_008_004.mp3",
      "text": "تُوبُوٓا۟",
      "translation": "bertaubatlah kamu",
      "transliteration": "tūbū"
    },
    {
      "id": 8994,
      "line_number": 1,
      "audio_url": "https://audio.qurancdn.com/wbw/066_008_005.mp3",
      "text": "إِلَى",
      "translation": "kepada",
      "transliteration": "ilā"
    },
    {
      "id": 8995,
      "line_number": 1,
      "audio_url": "https://audio.qurancdn.com/wbw/066_008_006.mp3",
      "text": "ٱللَّهِ",
      "translation": "Allah",
      "transliteration": "l-lahi"
    },
    {
      "id": 8996,
      "line_number": 1,
      "audio_url": "https://audio.qurancdn.com/wbw/066_008_007.mp3",
      "text": "تَوْبَةًۭ",
      "translation": "taubat",
      "transliteration": "tawbatan"
    },
    {
      "id": 8997,
      "line_number": 1,
      "audio_url": "https://audio.qurancdn.com/wbw/066_008_008.mp3",
      "text": "نَّصُوحًا",
      "translation": "sungguh-sungguh dan ikhlas",
      "transliteration": "naṣūḥan"
    },
    {
      "id": 8998,
      "line_number": 1,
      "audio_url": "https://audio.qurancdn.com/wbw/066_008_009.mp3",
      "text": "عَسَىٰ",
      "translation": "boleh jadi/mudah-mudahan",
      "transliteration": "ʿasā"
    },
    {
      "id": 8999,
      "line_number": 1,
      "audio_url": "https://audio.qurancdn.com/wbw/066_008_010.mp3",
      "text": "رَبُّكُمْ",
      "translation": "Tuhan kalian",
      "transliteration": "rabbukum"
    },
    {
      "id": 9000,
      "line_number": 2,
      "audio_url": "https://audio.qurancdn.com/wbw/066_008_011.mp3",
      "text": "أَن",
      "translation": "akan",
      "transliteration": "an"
    },
    {
      "id": 9001,
      "line_number": 2,
      "audio_url": "https://audio.qurancdn.com/wbw/066_008_012.mp3",
      "text": "يُكَفِّرَ",
      "translation": "menghapus/menutupi",
      "transliteration": "yukaffira"
    },
    {
      "id": 9002,
      "line_number": 2,
      "audio_url": "https://audio.qurancdn.com/wbw/066_008_013.mp3",
      "text": "عَنكُمْ",
      "translation": "dari kalian",
      "transliteration": "ʿankum"
    },
    {
      "id": 9003,
      "line_number": 2,
      "audio_url": "https://audio.qurancdn.com/wbw/066_008_014.mp3",
      "text": "سَيِّـَٔاتِكُمْ",
      "translation": "kesalahan-kesalahanmu",
      "transliteration": "sayyiātikum"
    },
    {
      "id": 9004,
      "line_number": 2,
      "audio_url": "https://audio.qurancdn.com/wbw/066_008_015.mp3",
      "text": "وَيُدْخِلَكُمْ",
      "translation": "dan akan memasukkan kamu",
      "transliteration": "wayud'khilakum"
    },
    {
      "id": 9005,
      "line_number": 2,
      "audio_url": "https://audio.qurancdn.com/wbw/066_008_016.mp3",
      "text": "جَنَّـٰتٍۢ",
      "translation": "surga-surga",
      "transliteration": "jannātin"
    },
    {
      "id": 9006,
      "line_number": 2,
      "audio_url": "https://audio.qurancdn.com/wbw/066_008_017.mp3",
      "text": "تَجْرِى",
      "translation": "mengalir",
      "transliteration": "tajrī"
    },
    {
      "id": 9007,
      "line_number": 3,
      "audio_url": "https://audio.qurancdn.com/wbw/066_008_018.mp3",
      "text": "مِن",
      "translation": "dari",
      "transliteration": "min"
    },
    {
      "id": 9008,
      "line_number": 3,
      "audio_url": "https://audio.qurancdn.com/wbw/066_008_019.mp3",
      "text": "تَحْتِهَا",
      "translation": "bawahnya",
      "transliteration": "taḥtihā"
    },
    {
      "id": 9009,
      "line_number": 3,
      "audio_url": "https://audio.qurancdn.com/wbw/066_008_020.mp3",
      "text": "ٱلْأَنْهَـٰرُ",
      "translation": "sungai-sungai",
      "transliteration": "l-anhāru"
    },
    {
      "id": 9010,
      "line_number": 3,
      "audio_url": "https://audio.qurancdn.com/wbw/066_008_021.mp3",
      "text": "يَوْمَ",
      "translation": "pada hari",
      "transliteration": "yawma"
    },
    {
      "id": 9011,
      "line_number": 3,
      "audio_url": "https://audio.qurancdn.com/wbw/066_008_022.mp3",
      "text": "لَا",
      "translation": "tidak",
      "transliteration": "lā"
    },
    {
      "id": 9012,
      "line_number": 3,
      "audio_url": "https://audio.qurancdn.com/wbw/066_008_023.mp3",
      "text": "يُخْزِى",
      "translation": "menghinakan",
      "transliteration": "yukh'zī"
    },
    {
      "id": 9013,
      "line_number": 3,
      "audio_url": "https://audio.qurancdn.com/wbw/066_008_024.mp3",
      "text": "ٱللَّهُ",
      "translation": "Allah",
      "transliteration": "l-lahu"
    },
    {
      "id": 9014,
      "line_number": 3,
      "audio_url": "https://audio.qurancdn.com/wbw/066_008_025.mp3",
      "text": "ٱلنَّبِىَّ",
      "translation": "Nabi",
      "transliteration": "l-nabiya"
    },
    {
      "id": 9015,
      "line_number": 3,
      "audio_url": "https://audio.qurancdn.com/wbw/066_008_026.mp3",
      "text": "وَٱلَّذِينَ",
      "translation": "dan orang-orang yang",
      "transliteration": "wa-alladhīna"
    },
    {
      "id": 9016,
      "line_number": 3,
      "audio_url": "https://audio.qurancdn.com/wbw/066_008_027.mp3",
      "text": "ءَامَنُوا۟",
      "translation": "beriman",
      "transliteration": "āmanū"
    },
    {
      "id": 9017,
      "line_number": 4,
      "audio_url": "https://audio.qurancdn.com/wbw/066_008_028.mp3",
      "text": "مَعَهُۥ ۖ",
      "translation": "bersama dia",
      "transliteration": "maʿahu"
    },
    {
      "id": 9019,
      "line_number": 4,
      "audio_url": "https://audio.qurancdn.com/wbw/066_008_030.mp3",
      "text": "نُورُهُمْ",
      "translation": "cahaya mereka",
      "transliteration": "nūruhum"
    },
    {
      "id": 9020,
      "line_number": 4,
      "audio_url": "https://audio.qurancdn.com/wbw/066_008_031.mp3",
      "text": "يَسْعَىٰ",
      "translation": "berjalan/bersinar",
      "transliteration": "yasʿā"
    },
    {
      "id": 9021,
      "line_number": 4,
      "audio_url": "https://audio.qurancdn.com/wbw/066_008_032.mp3",
      "text": "بَيْنَ",
      "translation": "diantara",
      "transliteration": "bayna"
    },
    {
      "id": 9022,
      "line_number": 4,
      "audio_url": "https://audio.qurancdn.com/wbw/066_008_033.mp3",
      "text": "أَيْدِيهِمْ",
      "translation": "hadapan mereka",
      "transliteration": "aydīhim"
    },
    {
      "id": 9023,
      "line_number": 4,
      "audio_url": "https://audio.qurancdn.com/wbw/066_008_034.mp3",
      "text": "وَبِأَيْمَـٰنِهِمْ",
      "translation": "dan di sebelah kanan mereka",
      "transliteration": "wabi-aymānihim"
    },
    {
      "id": 9024,
      "line_number": 4,
      "audio_url": "https://audio.qurancdn.com/wbw/066_008_035.mp3",
      "text": "يَقُولُونَ",
      "translation": "mereka mengatakan",
      "transliteration": "yaqūlūna"
    },
    {
      "id": 9025,
      "line_number": 4,
      "audio_url": "https://audio.qurancdn.com/wbw/066_008_036.mp3",
      "text": "رَبَّنَآ",
      "translation": "ya Tuhan kami",
      "transliteration": "rabbanā"
    },
    {
      "id": 9026,
      "line_number": 5,
      "audio_url": "https://audio.qurancdn.com/wbw/066_008_037.mp3",
      "text": "أَتْمِمْ",
      "translation": "sempurnakanlah",
      "transliteration": "atmim"
    },
    {
      "id": 9027,
      "line_number": 5,
      "audio_url": "https://audio.qurancdn.com/wbw/066_008_038.mp3",
      "text": "لَنَا",
      "translation": "bagi kami",
      "transliteration": "lanā"
    },
    {
      "id": 9028,
      "line_number": 5,
      "audio_url": "https://audio.qurancdn.com/wbw/066_008_039.mp3",
      "text": "نُورَنَا",
      "translation": "cahaya kami",
      "transliteration": "nūranā"
    },
    {
      "id": 9029,
      "line_number": 5,
      "audio_url": "https://audio.qurancdn.com/wbw/066_008_040.mp3",
      "text": "وَٱغْفِرْ",
      "translation": "dan ampunilah",
      "transliteration": "wa-igh'fir"
    },
    {
      "id": 9030,
      "line_number": 5,
      "audio_url": "https://audio.qurancdn.com/wbw/066_008_041.mp3",
      "text": "لَنَآ ۖ",
      "translation": "bagi kami",
      "transliteration": "lanā"
    },
    {
      "id": 9032,
      "line_number": 5,
      "audio_url": "https://audio.qurancdn.com/wbw/066_008_043.mp3",
      "text": "إِنَّكَ",
      "translation": "sesungguhnya Engkau",
      "transliteration": "innaka"
    },
    {
      "id": 9033,
      "line_number": 5,
      "audio_url": "https://audio.qurancdn.com/wbw/066_008_044.mp3",
      "text": "عَلَىٰ",
      "translation": "atas",
      "transliteration": "ʿalā"
    },
    {
      "id": 9034,
      "line_number": 5,
      "audio_url": "https://audio.qurancdn.com/wbw/066_008_045.mp3",
      "text": "كُلِّ",
      "translation": "segala",
      "transliteration": "kulli"
    },
    {
      "id": 9035,
      "line_number": 5,
      "audio_url": "https://audio.qurancdn.com/wbw/066_008_046.mp3",
      "text": "شَىْءٍۢ",
      "translation": "sesuatu",
      "transliteration": "shayin"
    },
    {
      "id": 9036,
      "line_number": 5,
      "audio_url": "https://audio.qurancdn.com/wbw/066_008_047.mp3",
      "text": "قَدِيرٌۭ",
      "translation": "Maha Kuasa",
      "transliteration": "qadīrun"
    },
    {
      "id": 9037,
      "line_number": 5,
      "audio_url": null,
      "text": "٨",
      "translation": "(8)",
      "transliteration": null
    }
  ],
  "translation": {
    "text": "Hai orang-orang yang beriman, bertobatlah kepada Allah dengan tobat yang semurni-murninya, mudah-mudahan Tuhan kamu akan menghapus kesalahan-kesalahanmu dan memasukkanmu ke dalam surga yang mengalir di bawahnya sungai-sungai, pada hari ketika Allah tidak menghinakan nabi dan orang-orang yang beriman bersama dia; sedang cahaya mereka memancar di hadapan dan di sebelah kanan mereka, sambil mereka mengatakan, \"Ya Tuhan kami, sempurnakanlah bagi kami cahaya kami dan ampunilah kami; Sesungguhnya Engkau Maha Kuasa atas segala sesuatu\".",
    "resource_name": "King Fahad Quran Complex"
  },
  "transliteration": "Yā ayyuhal-lażīna āmanū tūbū ilallāhi taubatan naṣūḥā(n), ‘asā rabbukum ay yukaffira ‘ankum sayyi'ātikum wa yudkhilakum jannātin tajrī min taḥtihal-anhār(u), yauma lā yukhzillāhun-nabiyya wal-lażīna āmanū ma‘ah(ū), nūruhum yas‘ā baina aidīhim wa bi'aimānihim yaqūlūna rabbanā atmim lanā nūranā wagfir lanā, innaka ‘alā kulli syai'in qadīr(un)."
}