{
  "id": 3333,
  "chapter_id": 28,
  "verse_key": "28:81",
  "hizb_number": 40,
  "rub_el_hizb_number": 158,
  "ruku_number": 341,
  "manzil_number": 5,
  "page_number": 395,
  "juz_number": 20,
  "text_uthmani": "فَخَسَفْنَا بِهِۦ وَبِدَارِهِ ٱلْأَرْضَ فَمَا كَانَ لَهُۥ مِن فِئَةٍ يَنصُرُونَهُۥ مِن دُونِ ٱللَّهِ وَمَا كَانَ مِنَ ٱلْمُنتَصِرِينَ",
  "audio_url": "https://download.quranicaudio.com/qdc/mishari_al_afasy/murattal/28.mp3",
  "words": [
    {
      "id": 64671,
      "line_number": 7,
      "audio_url": "https://audio.qurancdn.com/wbw/028_081_001.mp3",
      "text": "فَخَسَفْنَا",
      "translation": "maka Kami benamkan",
      "transliteration": "fakhasafnā"
    },
    {
      "id": 64672,
      "line_number": 8,
      "audio_url": "https://audio.qurancdn.com/wbw/028_081_002.mp3",
      "text": "بِهِۦ",
      "translation": "dengannya",
      "transliteration": "bihi"
    },
    {
      "id": 64673,
      "line_number": 8,
      "audio_url": "https://audio.qurancdn.com/wbw/028_081_003.mp3",
      "text": "وَبِدَارِهِ",
      "translation": "dan dengan rumahnya",
      "transliteration": "wabidārihi"
    },
    {
      "id": 64674,
      "line_number": 8,
      "audio_url": "https://audio.qurancdn.com/wbw/028_081_004.mp3",
      "text": "ٱلْأَرْضَ",
      "translation": "bumi",
      "transliteration": "l-arḍa"
    },
    {
      "id": 64675,
      "line_number": 8,
      "audio_url": "https://audio.qurancdn.com/wbw/028_081_005.mp3",
      "text": "فَمَا",
      "translation": "maka tidak",
      "transliteration": "famā"
    },
    {
      "id": 64676,
      "line_number": 8,
      "audio_url": "https://audio.qurancdn.com/wbw/028_081_006.mp3",
      "text": "كَانَ",
      "translation": "ada",
      "transliteration": "kāna"
    },
    {
      "id": 64677,
      "line_number": 8,
      "audio_url": "https://audio.qurancdn.com/wbw/028_081_007.mp3",
      "text": "لَهُۥ",
      "translation": "baginya",
      "transliteration": "lahu"
    },
    {
      "id": 64678,
      "line_number": 8,
      "audio_url": "https://audio.qurancdn.com/wbw/028_081_008.mp3",
      "text": "مِن",
      "translation": "dari",
      "transliteration": "min"
    },
    {
      "id": 64679,
      "line_number": 8,
      "audio_url": "https://audio.qurancdn.com/wbw/028_081_009.mp3",
      "text": "فِئَةٍۢ",
      "translation": "golongan",
      "transliteration": "fi-atin"
    },
    {
      "id": 64680,
      "line_number": 8,
      "audio_url": "https://audio.qurancdn.com/wbw/028_081_010.mp3",
      "text": "يَنصُرُونَهُۥ",
      "translation": "mereka menolongnya",
      "transliteration": "yanṣurūnahu"
    },
    {
      "id": 64681,
      "line_number": 8,
      "audio_url": "https://audio.qurancdn.com/wbw/028_081_011.mp3",
      "text": "مِن",
      "translation": "dari",
      "transliteration": "min"
    },
    {
      "id": 64682,
      "line_number": 8,
      "audio_url": "https://audio.qurancdn.com/wbw/028_081_012.mp3",
      "text": "دُونِ",
      "translation": "selain",
      "transliteration": "dūni"
    },
    {
      "id": 64683,
      "line_number": 9,
      "audio_url": "https://audio.qurancdn.com/wbw/028_081_013.mp3",
      "text": "ٱللَّهِ",
      "translation": "Allah",
      "transliteration": "l-lahi"
    },
    {
      "id": 64684,
      "line_number": 9,
      "audio_url": "https://audio.qurancdn.com/wbw/028_081_014.mp3",
      "text": "وَمَا",
      "translation": "dan tidak",
      "transliteration": "wamā"
    },
    {
      "id": 64685,
      "line_number": 9,
      "audio_url": "https://audio.qurancdn.com/wbw/028_081_015.mp3",
      "text": "كَانَ",
      "translation": "ada",
      "transliteration": "kāna"
    },
    {
      "id": 64686,
      "line_number": 9,
      "audio_url": "https://audio.qurancdn.com/wbw/028_081_016.mp3",
      "text": "مِنَ",
      "translation": "dari/termasuk",
      "transliteration": "mina"
    },
    {
      "id": 64687,
      "line_number": 9,
      "audio_url": "https://audio.qurancdn.com/wbw/028_081_017.mp3",
      "text": "ٱلْمُنتَصِرِينَ",
      "translation": "orang-orang yang dapat menolong",
      "transliteration": "l-muntaṣirīna"
    },
    {
      "id": 64688,
      "line_number": 9,
      "audio_url": null,
      "text": "٨١",
      "translation": "(81)",
      "transliteration": null
    }
  ],
  "translation": {
    "text": "Maka Kami benamkanlah Qārūn beserta rumahnya ke dalam bumi.  Maka tidak ada baginya suatu golongan pun yang menolongnya terhadap azab Allah.  Dan tiadalah ia termasuk orang-orang (yang dapat) membela (dirinya).",
    "resource_name": "King Fahad Quran Complex"
  },
  "transliteration": "Fakhasafnā bihī wa bidārihil-arḍ(a), famā kāna lahū min fi'atiy yanṣurūnahū min dūnillāh(i), wa mā kāna minal-muntaṣirīn(a)."
}