{
  "id": 3682,
  "chapter_id": 35,
  "verse_key": "35:22",
  "hizb_number": 44,
  "rub_el_hizb_number": 175,
  "ruku_number": 380,
  "manzil_number": 5,
  "page_number": 437,
  "juz_number": 22,
  "text_uthmani": "وَمَا يَسْتَوِى ٱلْأَحْيَآءُ وَلَا ٱلْأَمْوَٰتُ ۚ إِنَّ ٱللَّهَ يُسْمِعُ مَن يَشَآءُ ۖ وَمَآ أَنتَ بِمُسْمِعٍ مَّن فِى ٱلْقُبُورِ",
  "audio_url": "https://download.quranicaudio.com/qdc/mishari_al_afasy/murattal/35.mp3",
  "words": [
    {
      "id": 25314,
      "line_number": 2,
      "audio_url": "https://audio.qurancdn.com/wbw/035_022_001.mp3",
      "text": "وَمَا",
      "translation": "dan tidak",
      "transliteration": "wamā"
    },
    {
      "id": 25315,
      "line_number": 2,
      "audio_url": "https://audio.qurancdn.com/wbw/035_022_002.mp3",
      "text": "يَسْتَوِى",
      "translation": "sama",
      "transliteration": "yastawī"
    },
    {
      "id": 25316,
      "line_number": 2,
      "audio_url": "https://audio.qurancdn.com/wbw/035_022_003.mp3",
      "text": "ٱلْأَحْيَآءُ",
      "translation": "orang-orang yang hidup",
      "transliteration": "l-aḥyāu"
    },
    {
      "id": 25317,
      "line_number": 2,
      "audio_url": "https://audio.qurancdn.com/wbw/035_022_004.mp3",
      "text": "وَلَا",
      "translation": "dan tidak",
      "transliteration": "walā"
    },
    {
      "id": 25318,
      "line_number": 2,
      "audio_url": "https://audio.qurancdn.com/wbw/035_022_005.mp3",
      "text": "ٱلْأَمْوَٰتُ ۚ",
      "translation": "orang-orang yang mati",
      "transliteration": "l-amwātu"
    },
    {
      "id": 25320,
      "line_number": 3,
      "audio_url": "https://audio.qurancdn.com/wbw/035_022_007.mp3",
      "text": "إِنَّ",
      "translation": "sesungguhnya",
      "transliteration": "inna"
    },
    {
      "id": 25321,
      "line_number": 3,
      "audio_url": "https://audio.qurancdn.com/wbw/035_022_008.mp3",
      "text": "ٱللَّهَ",
      "translation": "Allah",
      "transliteration": "l-laha"
    },
    {
      "id": 25322,
      "line_number": 3,
      "audio_url": "https://audio.qurancdn.com/wbw/035_022_009.mp3",
      "text": "يُسْمِعُ",
      "translation": "menjadikan mendengar",
      "transliteration": "yus'miʿu"
    },
    {
      "id": 25323,
      "line_number": 3,
      "audio_url": "https://audio.qurancdn.com/wbw/035_022_010.mp3",
      "text": "مَن",
      "translation": "orang/siapa",
      "transliteration": "man"
    },
    {
      "id": 25324,
      "line_number": 3,
      "audio_url": "https://audio.qurancdn.com/wbw/035_022_011.mp3",
      "text": "يَشَآءُ ۖ",
      "translation": "Dia kehendaki",
      "transliteration": "yashāu"
    },
    {
      "id": 25326,
      "line_number": 3,
      "audio_url": "https://audio.qurancdn.com/wbw/035_022_013.mp3",
      "text": "وَمَآ",
      "translation": "dan tidaklah",
      "transliteration": "wamā"
    },
    {
      "id": 25327,
      "line_number": 3,
      "audio_url": "https://audio.qurancdn.com/wbw/035_022_014.mp3",
      "text": "أَنتَ",
      "translation": "kamu",
      "transliteration": "anta"
    },
    {
      "id": 25328,
      "line_number": 3,
      "audio_url": "https://audio.qurancdn.com/wbw/035_022_015.mp3",
      "text": "بِمُسْمِعٍۢ",
      "translation": "dengan menjadikan mendengar",
      "transliteration": "bimus'miʿin"
    },
    {
      "id": 25329,
      "line_number": 3,
      "audio_url": "https://audio.qurancdn.com/wbw/035_022_016.mp3",
      "text": "مَّن",
      "translation": "orang/siapa",
      "transliteration": "man"
    },
    {
      "id": 25330,
      "line_number": 3,
      "audio_url": "https://audio.qurancdn.com/wbw/035_022_017.mp3",
      "text": "فِى",
      "translation": "dalam",
      "transliteration": "fī"
    },
    {
      "id": 25331,
      "line_number": 3,
      "audio_url": "https://audio.qurancdn.com/wbw/035_022_018.mp3",
      "text": "ٱلْقُبُورِ",
      "translation": "kubur",
      "transliteration": "l-qubūri"
    },
    {
      "id": 25332,
      "line_number": 3,
      "audio_url": null,
      "text": "٢٢",
      "translation": "(22)",
      "transliteration": null
    }
  ],
  "translation": {
    "text": "dan tidak (pula) sama orang-orang yang hidup dan orang-orang yang mati.  Sesungguhnya Allah memberi pendengaran kepada siapa yang dikehendaki-Nya dan kamu sekali-kali tiada sanggup menjadikan orang yang di dalam kubur dapat mendengar <sup foot_note_id=\"1254\">1</sup>.",
    "resource_name": "King Fahad Quran Complex"
  },
  "timestamps": {
    "timestamp_from": 430520,
    "timestamp_to": 454420,
    "duration": 23900,
    "segments": [
      [
        1,
        430475,
        431075
      ],
      [
        2,
        431075,
        431825
      ],
      [
        3,
        431825,
        434515
      ],
      [
        4,
        434515,
        434775
      ],
      [
        5,
        434775,
        438345
      ],
      [
        6,
        438345,
        439515
      ],
      [
        7,
        439515,
        440205
      ],
      [
        8,
        440205,
        441045
      ],
      [
        9,
        441045,
        441155
      ],
      [
        10,
        441155,
        444694
      ],
      [
        11,
        444695,
        446795
      ],
      [
        12,
        446795,
        448035
      ],
      [
        13,
        448035,
        449105
      ],
      [
        14,
        449105,
        450075
      ],
      [
        14,
        450075,
        451085
      ],
      [
        15,
        451085,
        451305
      ],
      [
        16,
        451305,
        454320
      ]
    ]
  }
}