{
  "id": 1192,
  "chapter_id": 8,
  "verse_key": "8:32",
  "hizb_number": 18,
  "rub_el_hizb_number": 72,
  "ruku_number": 149,
  "manzil_number": 2,
  "page_number": 180,
  "juz_number": 9,
  "text_uthmani": "وَإِذْ قَالُوا۟ ٱللَّهُمَّ إِن كَانَ هَـٰذَا هُوَ ٱلْحَقَّ مِنْ عِندِكَ فَأَمْطِرْ عَلَيْنَا حِجَارَةً مِّنَ ٱلسَّمَآءِ أَوِ ٱئْتِنَا بِعَذَابٍ أَلِيمٍ",
  "audio_url": "https://download.quranicaudio.com/qdc/mishari_al_afasy/murattal/8.mp3",
  "words": [
    {
      "id": 34610,
      "line_number": 12,
      "audio_url": "https://audio.qurancdn.com/wbw/008_032_001.mp3",
      "text": "وَإِذْ",
      "translation": "dan ketika",
      "transliteration": "wa-idh"
    },
    {
      "id": 34611,
      "line_number": 12,
      "audio_url": "https://audio.qurancdn.com/wbw/008_032_002.mp3",
      "text": "قَالُوا۟",
      "translation": "mereka berkata",
      "transliteration": "qālū"
    },
    {
      "id": 34612,
      "line_number": 12,
      "audio_url": "https://audio.qurancdn.com/wbw/008_032_003.mp3",
      "text": "ٱللَّهُمَّ",
      "translation": "ya Allah",
      "transliteration": "l-lahuma"
    },
    {
      "id": 34613,
      "line_number": 12,
      "audio_url": "https://audio.qurancdn.com/wbw/008_032_004.mp3",
      "text": "إِن",
      "translation": "jika",
      "transliteration": "in"
    },
    {
      "id": 34614,
      "line_number": 12,
      "audio_url": "https://audio.qurancdn.com/wbw/008_032_005.mp3",
      "text": "كَانَ",
      "translation": "adalah",
      "transliteration": "kāna"
    },
    {
      "id": 34615,
      "line_number": 12,
      "audio_url": "https://audio.qurancdn.com/wbw/008_032_006.mp3",
      "text": "هَـٰذَا",
      "translation": "ini",
      "transliteration": "hādhā"
    },
    {
      "id": 34616,
      "line_number": 13,
      "audio_url": "https://audio.qurancdn.com/wbw/008_032_007.mp3",
      "text": "هُوَ",
      "translation": "dia",
      "transliteration": "huwa"
    },
    {
      "id": 34617,
      "line_number": 13,
      "audio_url": "https://audio.qurancdn.com/wbw/008_032_008.mp3",
      "text": "ٱلْحَقَّ",
      "translation": "benar",
      "transliteration": "l-ḥaqa"
    },
    {
      "id": 34618,
      "line_number": 13,
      "audio_url": "https://audio.qurancdn.com/wbw/008_032_009.mp3",
      "text": "مِنْ",
      "translation": "dari",
      "transliteration": "min"
    },
    {
      "id": 34619,
      "line_number": 13,
      "audio_url": "https://audio.qurancdn.com/wbw/008_032_010.mp3",
      "text": "عِندِكَ",
      "translation": "sisi Engkau",
      "transliteration": "ʿindika"
    },
    {
      "id": 34620,
      "line_number": 13,
      "audio_url": "https://audio.qurancdn.com/wbw/008_032_011.mp3",
      "text": "فَأَمْطِرْ",
      "translation": "maka hujanilah",
      "transliteration": "fa-amṭir"
    },
    {
      "id": 34621,
      "line_number": 13,
      "audio_url": "https://audio.qurancdn.com/wbw/008_032_012.mp3",
      "text": "عَلَيْنَا",
      "translation": "atas kami",
      "transliteration": "ʿalaynā"
    },
    {
      "id": 34622,
      "line_number": 13,
      "audio_url": "https://audio.qurancdn.com/wbw/008_032_013.mp3",
      "text": "حِجَارَةًۭ",
      "translation": "batu",
      "transliteration": "ḥijāratan"
    },
    {
      "id": 34623,
      "line_number": 13,
      "audio_url": "https://audio.qurancdn.com/wbw/008_032_014.mp3",
      "text": "مِّنَ",
      "translation": "dari",
      "transliteration": "mina"
    },
    {
      "id": 34624,
      "line_number": 13,
      "audio_url": "https://audio.qurancdn.com/wbw/008_032_015.mp3",
      "text": "ٱلسَّمَآءِ",
      "translation": "langit",
      "transliteration": "l-samāi"
    },
    {
      "id": 34625,
      "line_number": 14,
      "audio_url": "https://audio.qurancdn.com/wbw/008_032_016.mp3",
      "text": "أَوِ",
      "translation": "atau",
      "transliteration": "awi"
    },
    {
      "id": 34626,
      "line_number": 14,
      "audio_url": "https://audio.qurancdn.com/wbw/008_032_017.mp3",
      "text": "ٱئْتِنَا",
      "translation": "datangkan kepada kami",
      "transliteration": "i'tinā"
    },
    {
      "id": 34627,
      "line_number": 14,
      "audio_url": "https://audio.qurancdn.com/wbw/008_032_018.mp3",
      "text": "بِعَذَابٍ",
      "translation": "dengan azab",
      "transliteration": "biʿadhābin"
    },
    {
      "id": 34628,
      "line_number": 14,
      "audio_url": "https://audio.qurancdn.com/wbw/008_032_019.mp3",
      "text": "أَلِيمٍۢ",
      "translation": "sangat pedih",
      "transliteration": "alīmin"
    },
    {
      "id": 34629,
      "line_number": 14,
      "audio_url": null,
      "text": "٣٢",
      "translation": "(32)",
      "transliteration": null
    }
  ],
  "translation": {
    "text": "Dan (ingatlah), ketika mereka (orang-orang musyrik) berkata, \"Ya Allah, jika betul (Al-Qur`ān) ini, dialah yang benar dari sisi Engkau, maka hujanilah kami dengan batu dari langit, atau datangkanlah kepada kami azab yang pedih\".",
    "resource_name": "King Fahad Quran Complex"
  },
  "transliteration": "Wa iż qālullāhumma in kāna hāżā huwal-ḥaqqa min ‘indika fa amṭir ‘alainā ḥijāratam minas-samā'i awi'tinā bi‘ażābin alīm(in)."
}