{
  "id": 1161,
  "chapter_id": 8,
  "verse_key": "8:1",
  "hizb_number": 18,
  "rub_el_hizb_number": 71,
  "ruku_number": 146,
  "manzil_number": 2,
  "page_number": 177,
  "juz_number": 9,
  "text_uthmani": " يَسْـَٔلُونَكَ عَنِ ٱلْأَنفَالِ ۖ قُلِ ٱلْأَنفَالُ لِلَّهِ وَٱلرَّسُولِ ۖ فَٱتَّقُوا۟ ٱللَّهَ وَأَصْلِحُوا۟ ذَاتَ بَيْنِكُمْ ۖ وَأَطِيعُوا۟ ٱللَّهَ وَرَسُولَهُۥٓ إِن كُنتُم مُّؤْمِنِينَ",
  "audio_url": "https://download.quranicaudio.com/qdc/mishari_al_afasy/murattal/8.mp3",
  "words": [
    {
      "id": 193,
      "line_number": 3,
      "audio_url": "https://audio.qurancdn.com/wbw/008_001_001.mp3",
      "text": "يَسْـَٔلُونَكَ",
      "translation": "mereka akan menanyakan kepadamu",
      "transliteration": "yasalūnaka"
    },
    {
      "id": 194,
      "line_number": 3,
      "audio_url": "https://audio.qurancdn.com/wbw/008_001_002.mp3",
      "text": "عَنِ",
      "translation": "tentang",
      "transliteration": "ʿani"
    },
    {
      "id": 195,
      "line_number": 3,
      "audio_url": "https://audio.qurancdn.com/wbw/008_001_003.mp3",
      "text": "ٱلْأَنفَالِ ۖ",
      "translation": "harta rampasan perang",
      "transliteration": "l-anfāli"
    },
    {
      "id": 197,
      "line_number": 3,
      "audio_url": "https://audio.qurancdn.com/wbw/008_001_005.mp3",
      "text": "قُلِ",
      "translation": "katakanlah",
      "transliteration": "quli"
    },
    {
      "id": 198,
      "line_number": 3,
      "audio_url": "https://audio.qurancdn.com/wbw/008_001_006.mp3",
      "text": "ٱلْأَنفَالُ",
      "translation": "harta rampasan perang",
      "transliteration": "l-anfālu"
    },
    {
      "id": 199,
      "line_number": 3,
      "audio_url": "https://audio.qurancdn.com/wbw/008_001_007.mp3",
      "text": "لِلَّهِ",
      "translation": "kepunyaan Allah",
      "transliteration": "lillahi"
    },
    {
      "id": 200,
      "line_number": 3,
      "audio_url": "https://audio.qurancdn.com/wbw/008_001_008.mp3",
      "text": "وَٱلرَّسُولِ ۖ",
      "translation": "dan Rasul",
      "transliteration": "wal-rasūli"
    },
    {
      "id": 202,
      "line_number": 3,
      "audio_url": "https://audio.qurancdn.com/wbw/008_001_010.mp3",
      "text": "فَٱتَّقُوا۟",
      "translation": "maka bertakwalah kamu",
      "transliteration": "fa-ittaqū"
    },
    {
      "id": 203,
      "line_number": 3,
      "audio_url": "https://audio.qurancdn.com/wbw/008_001_011.mp3",
      "text": "ٱللَّهَ",
      "translation": "Allah",
      "transliteration": "l-laha"
    },
    {
      "id": 204,
      "line_number": 4,
      "audio_url": "https://audio.qurancdn.com/wbw/008_001_012.mp3",
      "text": "وَأَصْلِحُوا۟",
      "translation": "dan perbaikilah",
      "transliteration": "wa-aṣliḥū"
    },
    {
      "id": 205,
      "line_number": 4,
      "audio_url": "https://audio.qurancdn.com/wbw/008_001_013.mp3",
      "text": "ذَاتَ",
      "translation": "perhubungan",
      "transliteration": "dhāta"
    },
    {
      "id": 206,
      "line_number": 4,
      "audio_url": "https://audio.qurancdn.com/wbw/008_001_014.mp3",
      "text": "بَيْنِكُمْ ۖ",
      "translation": "diantara kamu",
      "transliteration": "baynikum"
    },
    {
      "id": 208,
      "line_number": 4,
      "audio_url": "https://audio.qurancdn.com/wbw/008_001_016.mp3",
      "text": "وَأَطِيعُوا۟",
      "translation": "dan taatlah kamu",
      "transliteration": "wa-aṭīʿū"
    },
    {
      "id": 209,
      "line_number": 4,
      "audio_url": "https://audio.qurancdn.com/wbw/008_001_017.mp3",
      "text": "ٱللَّهَ",
      "translation": "Allah",
      "transliteration": "l-laha"
    },
    {
      "id": 210,
      "line_number": 4,
      "audio_url": "https://audio.qurancdn.com/wbw/008_001_018.mp3",
      "text": "وَرَسُولَهُۥٓ",
      "translation": "dan RasulNya",
      "transliteration": "warasūlahu"
    },
    {
      "id": 211,
      "line_number": 4,
      "audio_url": "https://audio.qurancdn.com/wbw/008_001_019.mp3",
      "text": "إِن",
      "translation": "jika",
      "transliteration": "in"
    },
    {
      "id": 212,
      "line_number": 4,
      "audio_url": "https://audio.qurancdn.com/wbw/008_001_020.mp3",
      "text": "كُنتُم",
      "translation": "kalian adalah",
      "transliteration": "kuntum"
    },
    {
      "id": 213,
      "line_number": 5,
      "audio_url": "https://audio.qurancdn.com/wbw/008_001_021.mp3",
      "text": "مُّؤْمِنِينَ",
      "translation": "orang-orang yang beriman",
      "transliteration": "mu'minīna"
    },
    {
      "id": 214,
      "line_number": 5,
      "audio_url": null,
      "text": "١",
      "translation": "(1)",
      "transliteration": null
    }
  ],
  "translation": {
    "text": "Mereka menanyakan kepadamu tentang (pembagian) harta rampasan perang.  Katakanlah, \"Harta rampasan perang itu kepunyaan Allah dan rasul<sup foot_note_id=\"593\">1</sup>, sebab itu bertakwalah kepada Allah dan perbaikilah perhubungan di antara sesamamu, dan taatlah kepada Allah dan rasul-Nya jika kamu adalah orang-orang yang beriman\".",
    "resource_name": "King Fahad Quran Complex"
  },
  "transliteration": "Yas'alūnaka ‘anil-anfāl(i), qulil-anfālu lillāhi war-rasūl(i), fattaqullāha wa aṣliḥū żāta bainikum, wa aṭī‘ullāha wa rasūlahū in kuntum mu'minīn(a)."
}