{
  "id": 3739,
  "chapter_id": 36,
  "verse_key": "36:34",
  "hizb_number": 45,
  "rub_el_hizb_number": 177,
  "ruku_number": 385,
  "manzil_number": 5,
  "page_number": 442,
  "juz_number": 23,
  "text_uthmani": "وَجَعَلْنَا فِيهَا جَنَّـٰتٍ مِّن نَّخِيلٍ وَأَعْنَـٰبٍ وَفَجَّرْنَا فِيهَا مِنَ ٱلْعُيُونِ",
  "audio_url": "https://download.quranicaudio.com/qdc/mishari_al_afasy/murattal/36.mp3",
  "words": [
    {
      "id": 36725,
      "line_number": 7,
      "audio_url": "https://audio.qurancdn.com/wbw/036_034_001.mp3",
      "text": "وَجَعَلْنَا",
      "translation": "dan Kami jadikan",
      "transliteration": "wajaʿalnā"
    },
    {
      "id": 36726,
      "line_number": 7,
      "audio_url": "https://audio.qurancdn.com/wbw/036_034_002.mp3",
      "text": "فِيهَا",
      "translation": "di dalamnya/padanya",
      "transliteration": "fīhā"
    },
    {
      "id": 36727,
      "line_number": 7,
      "audio_url": "https://audio.qurancdn.com/wbw/036_034_003.mp3",
      "text": "جَنَّـٰتٍۢ",
      "translation": "kebun-kebun",
      "transliteration": "jannātin"
    },
    {
      "id": 36728,
      "line_number": 7,
      "audio_url": "https://audio.qurancdn.com/wbw/036_034_004.mp3",
      "text": "مِّن",
      "translation": "dari",
      "transliteration": "min"
    },
    {
      "id": 36729,
      "line_number": 7,
      "audio_url": "https://audio.qurancdn.com/wbw/036_034_005.mp3",
      "text": "نَّخِيلٍۢ",
      "translation": "korma",
      "transliteration": "nakhīlin"
    },
    {
      "id": 36730,
      "line_number": 8,
      "audio_url": "https://audio.qurancdn.com/wbw/036_034_006.mp3",
      "text": "وَأَعْنَـٰبٍۢ",
      "translation": "dan anggur",
      "transliteration": "wa-aʿnābin"
    },
    {
      "id": 36731,
      "line_number": 8,
      "audio_url": "https://audio.qurancdn.com/wbw/036_034_007.mp3",
      "text": "وَفَجَّرْنَا",
      "translation": "dan Kami pancarkan",
      "transliteration": "wafajjarnā"
    },
    {
      "id": 36732,
      "line_number": 8,
      "audio_url": "https://audio.qurancdn.com/wbw/036_034_008.mp3",
      "text": "فِيهَا",
      "translation": "di dalamnya",
      "transliteration": "fīhā"
    },
    {
      "id": 36733,
      "line_number": 8,
      "audio_url": "https://audio.qurancdn.com/wbw/036_034_009.mp3",
      "text": "مِنَ",
      "translation": "dari",
      "transliteration": "mina"
    },
    {
      "id": 36734,
      "line_number": 8,
      "audio_url": "https://audio.qurancdn.com/wbw/036_034_010.mp3",
      "text": "ٱلْعُيُونِ",
      "translation": "mata air",
      "transliteration": "l-ʿuyūni"
    },
    {
      "id": 36735,
      "line_number": 8,
      "audio_url": null,
      "text": "٣٤",
      "translation": "(34)",
      "transliteration": null
    }
  ],
  "translation": {
    "text": "Dan Kami jadikan padanya kebun-kebun kurma dan anggur dan Kami pancarkan padanya beberapa mata air,",
    "resource_name": "King Fahad Quran Complex"
  },
  "transliteration": "Wa ja‘alnā fīhā jannātim min nakhīliw wa a‘nābiw wa fajjarnā fīhā minal-‘uyūn(i)."
}